crescent/ext/docstrings/__init__.py
crescent/ext/docstrings/decorator.py
crescent/ext/docstrings/exceptions.py
crescent/ext/docstrings/style.py
crescent_ext_docstrings-0.2.2.dist-info/METADATA
crescent_ext_docstrings-0.2.2.dist-info/WHEEL
crescent_ext_docstrings-0.2.2.dist-info/RECORD
